medpro/__init__.py
medpro/_version.py
medpro/field.py
medpro/mesh.py
medpro/param.py
medpro-1.0.14.dist-info/LICENSE
medpro-1.0.14.dist-info/METADATA
medpro-1.0.14.dist-info/WHEEL
medpro-1.0.14.dist-info/top_level.txt
medpro-1.0.14.dist-info/RECORD
