Metadata-Version: 2.1
Name: medpro
Version: 1.0.14
Summary: Medcoupling based post processing tools
Home-page: https://github.com/ldallolio/medpro
Author: Luca Dall Olio
Author-email: luca.dallolio@gmail.com
License: MIT
Keywords: medpro,medcoupling
Classifier: Programming Language :: Python :: 3
License-File: LICENSE
Requires-Dist: medcoupling
